conftest.py
italy_geopop/__init__.py
italy_geopop/__version__.py
italy_geopop/_utils.py
italy_geopop/geopop.py
italy_geopop/pandas_extension.py
italy_geopop/data/2022_italy_geo_municipalities.feather
italy_geopop/data/2022_italy_geo_provinces.feather
italy_geopop/data/2022_italy_geo_regions.feather
italy_geopop/data/2022_italy_municipalities.feather
italy_geopop/data/2022_italy_pop.feather
italy_geopop/data/2022_italy_provinces.feather
italy_geopop/data/2022_italy_regions.feather
italy_geopop/data/2023_italy_geo_municipalities.feather
italy_geopop/data/2023_italy_geo_provinces.feather
italy_geopop/data/2023_italy_geo_regions.feather
italy_geopop/data/2023_italy_municipalities.feather
italy_geopop/data/2023_italy_pop.feather
italy_geopop/data/2023_italy_provinces.feather
italy_geopop/data/2023_italy_regions.feather
italy_geopop-0.6.2.dist-info/METADATA
italy_geopop-0.6.2.dist-info/WHEEL
italy_geopop-0.6.2.dist-info/licenses/LICENSE
italy_geopop-0.6.2.dist-info/RECORD
