Metadata-Version: 2.1
Name: italy-geopop
Version: 0.6.2
Summary: A python package that provides instant access to italian geospatial and population data.
Project-URL: Homepage, https://github.com/zenodallavalle/italy-geopop
Project-URL: Bug Tracker, https://github.com/zenodallavalle/italy-geopop/issues
Author-email: Zeno Dalla Valle <zenodallavalle@gmail.com>
License: Copyright 2018-2021 Openpolis
License-File: LICENSE
Classifier: Operating System :: OS Independent
Classifier: Programming Language :: Python :: 3
Requires-Python: >=3.10
Requires-Dist: geopandas>=0.12.2
Requires-Dist: numpy>=1.24.0
Requires-Dist: pandas>=1.5.0
Requires-Dist: pyarrow>=11.0.0
Provides-Extra: dev
Requires-Dist: matplotlib>=3.7.0; extra == 'dev'
Requires-Dist: pytest-assume>=2.4.3; extra == 'dev'
Requires-Dist: pytest>=7.2.1; extra == 'dev'
Requires-Dist: sphinx-rtd-theme>=1.2.0; extra == 'dev'
Requires-Dist: sphinx>=6.0.0; extra == 'dev'
Provides-Extra: docs
Requires-Dist: matplotlib>=3.7.0; extra == 'docs'
Requires-Dist: sphinx-rtd-theme>=1.2.0; extra == 'docs'
Requires-Dist: sphinx>=6.0.0; extra == 'docs'
Provides-Extra: docs-build-material
Requires-Dist: jupyter>=1.0.0; extra == 'docs-build-material'
Requires-Dist: matplotlib>=3.7.0; extra == 'docs-build-material'
Requires-Dist: sphinx-rtd-theme>=1.2.0; extra == 'docs-build-material'
Requires-Dist: sphinx>=6.0.0; extra == 'docs-build-material'
Provides-Extra: test
Requires-Dist: pytest-assume>=2.4.3; extra == 'test'
Requires-Dist: pytest>=7.2.1; extra == 'test'
